{
  "useid": "Mermaid",
  "furniture": [
    {
      "id": 0,
      "texture": "mermaid.png",
      "name": "Mermaid Vanity",
      "description": "You feel beautiful like a mermaid",
      "type": "decor",
      "price": 2000,
      "index": 0,
      "width": 1,
      "height": 2,
      "boxWidth": 1,
      "boxHeight": 1,
      "rotations": 4,
      "rotatedWidth": 1,
      "rotatedHeight": 2,
      "rotatedBoxHeight": 1,
      "rotatedBoxWidth": 1,
    },
    {
      "id": 1,
      "texture": "mermaid.png",
      "name": "Mermaid Chair",
      "description": "The scales on the back are surprisingly comfortable",
      "type": "chair",
      "price": 500,
      "index": 3,
      "width": 1,
      "height": 2,
      "boxWidth": 1,
      "boxHeight": 1,
      "rotations": 4,
      "rotatedWidth": 1,
      "rotatedHeight": 2,
      "rotatedBoxHeight": 1,
      "rotatedBoxWidth": 1,
    },
    {
      "id": 2,
      "texture": "mermaid.png",
      "name": "Mermaid Clock",
      "description": "You swear it sounds like the sea",
      "type": "painting",
      "price": 1000,
      "index": 6,
      "width": 1,
      "height": 2,
      "boxWidth": 1,
      "boxHeight": 2,
      "rotations": 1
    },
    {
      "id": 3,
      "texture": "mermaid.png",
      "name": "Mermaid Rug",
      "description": "Glitters",
      "type": "rug",
      "price": 100,
      "index": 7,
      "width": 2,
      "height": 2,
      "boxWidth": 2,
      "boxHeight": 2,
      "rotations": 1
    },
    {
      "id": 4,
      "texture": "mermaid.png",
      "name": "Banana Flower Basket",
      "description": "Makes your room smell like bananas",
      "type": "decor",
      "price": 500,
      "index": 9,
      "width": 1,
      "height": 2,
      "boxWidth": 1,
      "boxHeight": 1,
      "rotations": 1
    },
    {
      "id": 5,
      "texture": "mermaid.png",
      "name": "Durian Flower Basket",
      "description": "You feel like you're in paradise",
      "type": "decor",
      "price": 500,
      "index": 10,
      "width": 1,
      "height": 2,
      "boxWidth": 1,
      "boxHeight": 1,
      "rotations": 1
    },
    {
      "id": 6,
      "texture": "mermaid.png",
      "name": "Mermaid Sofa",
      "description": "Much comfier than a rock in the sea",
      "type": "couch",
      "price": 3000,
      "index": 26,
      "width": 3,
      "height": 2,
      "boxWidth": 3,
      "boxHeight": 2,
      "rotations": 4
    },
    {
      "id": 7,
      "texture": "mermaid.png",
      "name": "Mermaid Table",
      "description": "Glitters",
      "type": "Table",
      "price": 1000,
      "index": 34,
      "width": 2,
      "height": 3,
      "boxWidth": 2,
      "boxHeight": 2,
      "rotations": 1
    },
    {
      "id": 8,
      "texture": "mermaid.png",
      "name": "Mermaid Shelf",
      "description": "Includes a collection of stuff",
      "type": "decor",
      "price": 1000,
      "index": 65,
      "width": 2,
      "height": 3,
      "boxWidth": 2,
      "boxHeight": 2,
      "rotations": 4,
      "rotatedWidth": 1,
      "rotatedHeight": 2,
      "rotatedBoxHeight": 1,
      "rotatedBoxWidth": 3,
    },
    {
      "id": 9,
      "texture": "mermaid.png",
      "name": "Mermaid Dresser",
      "description": "For keeping all your mermaid tails and sea shells",
      "type": "Dresser",
      "price": 1000,
      "index": 70,
      "width": 2,
      "height": 3,
      "boxWidth": 2,
      "boxHeight": 3,
      "rotations": 4,
      "rotatedWidth": 1,
      "rotatedHeight": 1,
      "rotatedBoxHeight": 1,
      "rotatedBoxWidth": 3,
    },
    {
      "id": 10,
      "texture": "mermaid.png",
      "name": "Mermaid Wardrobe",
      "description": "Always need more room for shells",
      "type": "Dresser",
      "price": 1000,
      "index": 75,
      "width": 1,
      "height": 3,
      "boxWidth": 1,
      "boxHeight": 1,
      "rotations": 1
    },
    {
      "id": 11,
      "texture": "mermaid.png",
      "name": "Mermaid Lamp",
      "description": "Shines like the sun on the waves",
      "type": "Lamp",
      "price": 1000,
      "index": 76,
      "width": 1,
      "height": 3,
      "boxWidth": 1,
      "boxHeight": 1,
      "rotations": 1
    },
    {
      "id": 12,
      "texture": "mermaid.png",
      "name": "Mermaid Floor",
      "description": "Like walking on the ocean floor",
      "type": "rug",
      "price": 1000,
      "index": 104,
      "width": 3,
      "height": 2,
      "boxWidth": 3,
      "boxHeight": 2,
      "rotations": 1
    }
  ]
}