{
  "Name": "Yerba Mate Leaves",
  "Description": "A member of the holly family, this subtropical plant contains a natural stimulant that's used in some drinks and is increasingly available around the world.",
  "Category": "Vegetable",
  "Edibility": 45,
  "Price": 225,
  "IsColored": false,
  "GiftTastes": {
    "Love": ["Caroline", "Leah",],
    "Like": ["Abigail", "Dwarf", "Demetrius", "Gus", "Harvey", "Jodi", "Kent", "Elliott", "Linus", "Pam", "Robin", "Sandy", "Shane", "Emily", "Sebastian", "Alex", "Caroline", "Evelyn", "George", "Krobus", "Lewis", "Marnie", "Maru", "Pierre", "Sam", "Willy", "Wizard"],
    "Neutral": ["Haley", "Clint"],
    "Dislike": ["Jas", "Vincent"],
  },
  "Recipe": null,
  "NameLocalization": { 
    // "es": "",
     "ko": "셰르바 마테 잎",
    // "de": "",
    // "fr": "",
    // "hu": "",
    // "it": "",
    // "ja": "",
    // "pt": "",
    // "ru": "",
    // "tr": "",
    // "zh": "",
     },
 "DescriptionLocalization": { 
    // "es": "",
    "ko": "파라과이의 호랑가시나무라고도 한다. 카페인이 풍부하여 전세계적으로 점점 널리 사용되는 추세이다. ",
     //"de": "",
    // "fr": "",
    // "hu": "",
    // "it": "",
    // "ja": "",
    // "pt": "",
    // "ru": "",
    // "tr": "",
    // "zh": "",
    },
}
